ecas/__init__.py
ecas/__main__.py
ecas/ecas.py
ecas-0.3.3.dist-info/entry_points.txt
ecas-0.3.3.dist-info/LICENSE
ecas-0.3.3.dist-info/WHEEL
ecas-0.3.3.dist-info/METADATA
ecas-0.3.3.dist-info/RECORD
