Metadata-Version: 2.1
Name: ecas
Version: 0.3.3
Summary: A CLI to directly read your PR status
Home-page: https://github.com/pievalentin/ecas
License: MIT
Author: Pierre Valentin
Author-email: pievalentin@gmail.com
Requires-Python: >=3.8,<4.0
Classifier: License :: OSI Approved :: MIT License
Classifier: Programming Language :: Python :: 3
Classifier: Programming Language :: Python :: 3.8
Classifier: Programming Language :: Python :: 3.9
Requires-Dist: beautifulsoup4 (>=4.9.3,<5.0.0)
Requires-Dist: click (>=8.0.1,<9.0.0)
Requires-Dist: requests (>=2.25.1,<3.0.0)
Project-URL: Repository, https://github.com/pievalentin/ecas
